src/__init__.py
src/main.py
tok_dl-0.0.4.dist-info/METADATA
tok_dl-0.0.4.dist-info/WHEEL
tok_dl-0.0.4.dist-info/entry_points.txt
tok_dl-0.0.4.dist-info/licenses/LICENSE
tok_dl-0.0.4.dist-info/RECORD
