Metadata-Version: 2.4
Name: tok-dl
Version: 0.0.4
Summary: Tok-DL: A TikTok Downloader that actually works
Project-URL: Homepage, https://github.com/sweepies/tok-dl
Project-URL: Repository, https://github.com/sweepies/tok-dl.git
Project-URL: Issues, https://github.com/sweepies/tok-dl/issues
Author-email: Sweepy <git@sweepy.dev>
License:                     GNU GENERAL PUBLIC LICENSE
License-File: LICENSE
Keywords: archiver,downloader,tiktok
Classifier: Operating System :: OS Independent
Classifier: Programming Language :: Python :: 3
Requires-Python: >=3.8
Requires-Dist: click
Requires-Dist: loguru
Requires-Dist: pause
Requires-Dist: requests
Requires-Dist: validators
